<data>
    <title>Битка при Клокотница</title>
    <exactDate>1230-03-09</exactDate>
    <latitude>41.992279</latitude>
    <longitude>25.499058</longitude>
    <description><![CDATA[
    Нарастващото влияние на Иван Асен II върху Сърбия и Латинската империя започва сериозно да безпокои епирския владетел. Особено подозрителни и опасни са за него стремежите на българския цар да се намеси във вътрешните работи на латинците и да стане опекун на малолетния император Балдуин II, като му даде за съпруга дъщеря си Елена. Този план може да осуети намеренията на Теодор Комнин и затова той насочва войската си срещу България с надеждата за бърза и лека победа. Теодор Комнин е толкова сигурен в победата си, че взема в похода цялото си семейство и куп придворни.
    ]]></description>
</data>